{
  "sections": {
    "main": {
      "type": "main-page",
      "disabled": true,
      "settings": {
        "show_title": false,
        "page_width": "medium"
      }
    },
    "166142612467b926f1": {
      "type": "image-with-text-block",
      "settings": {
        "reveal_on_scroll": true,
        "image": "shopify:\/\/shop_images\/the-fact-in-your-stars-desktop.jpg",
        "mobile_image": "shopify:\/\/shop_images\/the-fact-in-your-stars-mobile.jpg",
        "alt_text": "",
        "enable_text": false,
        "subheading": "Subheading",
        "title": "Image with text block",
        "content": "<p>Use block text to give your customers insight into your brand. Select impactful text that relates to your brand and story.<\/p>",
        "button_text": "",
        "button_link": "",
        "background_type": "full_width",
        "text_position": "left",
        "text_alignment": "center",
        "text_background": "rgba(0,0,0,0)",
        "text_color": "rgba(0,0,0,0)",
        "button_background": "rgba(0,0,0,0)",
        "button_text_color": "rgba(0,0,0,0)"
      }
    },
    "286454d2-298d-4b02-a57e-1e2e080525a3": {
      "type": "custom-popup-modal",
      "settings": {
        "landing_based": true,
        "popup_id": "",
        "button_id": "SUBSCRIBE",
        "popup_image": "shopify:\/\/shop_images\/Asset_2_288x-8_5_small_a89089b1-2cee-4487-8d84-1dd4e7e6f6cc.png",
        "popup_backgroung": "#ffffff",
        "popup_text": "",
        "clevertap_id": "Horoscope subscription"
      }
    },
    "d05790c8-0ca6-4f8b-8e27-93b21458a907": {
      "type": "custom-html",
      "settings": {
        "subheading": "",
        "title": "",
        "html": "<style>\n\n[aria-expanded=true]>.animated-plus:before, [reveal]{opacity: 1 !important;}\n<\/style>",
        "add_vertical_spacing": false,
        "background_type": "full_width",
        "background": "rgba(0,0,0,0)",
        "text_color": "rgba(0,0,0,0)"
      }
    },
    "14bdc7d5-6182-4515-9276-fe78f37a2325": {
      "type": "custom-html",
      "disabled": true,
      "settings": {
        "subheading": "",
        "title": "",
        "html": "<style>\n.shopify-section.shopify-section--custom-html .container{padding:0!important;cursor: pointer;}\n<\/style>\n<div class=\"image-with-text-block__image-wrapper\">\n<img class=\"image-with-text-block__image hidden-lap-and-up\" alt=\"\" loading=\"lazy\" sizes=\"100vw\" height=\"260\" width=\"1300\" src=\"https:\/\/sfycdn.speedsize.com\/cf3f0159-e4fe-46aa-b575-b1143edf3fa7\/https:\/\/cdn.shopify.com\/s\/files\/1\/0057\/8938\/4802\/files\/mob_2e4d7196-17c9-49fa-adbd-896968c06e46.png?v=1668766500\">\n<img alt=\"\" class=\"image-with-text-block__image  hidden-pocket\" loading=\"lazy\" sizes=\"(max-width: 999px) 100vw, 100vw\" height=\"422\" width=\"2000\" src=\"https:\/\/sfycdn.speedsize.com\/cf3f0159-e4fe-46aa-b575-b1143edf3fa7\/https:\/\/cdn.shopify.com\/s\/files\/1\/0057\/8938\/4802\/files\/landing-page_06_2000x.png?v=1668676320\">\n<\/div>",
        "add_vertical_spacing": true,
        "background_type": "full_width",
        "background": "rgba(0,0,0,0)",
        "text_color": "rgba(0,0,0,0)"
      }
    },
    "4cab6d47-5189-424f-9160-e5479f512531": {
      "type": "custom-popup-modal",
      "disabled": true,
      "settings": {
        "landing_based": false,
        "popup_id": ".shopify-section.shopify-section--custom-html .container",
        "button_id": "Subscribe",
        "popup_image": "shopify:\/\/shop_images\/Rectangle_1285.png",
        "popup_backgroung": "#000000",
        "popup_text": "Enjoyed reading your horoscope? Subscribe to get more fun emails in your inbox.",
        "clevertap_id": ""
      }
    }
  },
  "order": [
    "main",
    "166142612467b926f1",
    "286454d2-298d-4b02-a57e-1e2e080525a3",
    "d05790c8-0ca6-4f8b-8e27-93b21458a907",
    "14bdc7d5-6182-4515-9276-fe78f37a2325",
    "4cab6d47-5189-424f-9160-e5479f512531"
  ]
}
